jquery_unparam.py
setup.py
jquery_unparam.egg-info/PKG-INFO
jquery_unparam.egg-info/SOURCES.txt
jquery_unparam.egg-info/dependency_links.txt
jquery_unparam.egg-info/pbr.json
jquery_unparam.egg-info/top_level.txt