Metadata-Version: 1.0
Name: jquery-unparam
Version: 2.0.0
Summary: A python library to parse jquery.param() string.
Home-page: https://bitbucket.org/k_bx/jquery-unparam/
Author: Konstantine Rybnikov
Author-email: k-bx@k-bx.com
License: BSD
Platform: any
